erics_cameras/__init__.py
erics_cameras/calibrate.py
erics_cameras/camera.py
erics_cameras/csi_cam.py
erics_cameras/gst_cam.py
erics_cameras/mock_cam.py
erics_cameras/rtsp_cam.py
erics_cameras/types.py
erics_cameras/usb_cam.py
erics_cameras/gazebo/__init__.py
erics_cameras/gazebo/gazebo_cam.py
erics_cameras-1.0.2.dist-info/METADATA
erics_cameras-1.0.2.dist-info/WHEEL
erics_cameras-1.0.2.dist-info/top_level.txt
erics_cameras-1.0.2.dist-info/RECORD
