Metadata-Version: 2.4
Name: erics_cameras
Version: 1.0.2
Summary: Eric's camera library, focused on robotics
Author: Eric Pedley
Project-URL: source, https://github.com/EricPedley/erics_cameras
